{"trial_id": "3", "hyperparameters": {"space": [{"class_name": "Int", "config": {"name": "num_layers", "default": null, "conditions": [], "min_value": 1, "max_value": 3, "step": 1, "sampling": "linear"}}, {"class_name": "Int", "config": {"name": "units_0", "default": null, "conditions": [], "min_value": 32, "max_value": 512, "step": 32, "sampling": "linear"}}, {"class_name": "Int", "config": {"name": "units_1", "default": null, "conditions": [], "min_value": 32, "max_value": 512, "step": 32, "sampling": "linear"}}], "values": {"num_layers": 2, "units_0": 480, "units_1": 256}}, "metrics": {"metrics": {"accuracy": {"direction": "max", "observations": [{"value": [0.9769970774650574], "step": 4}]}, "loss": {"direction": "min", "observations": [{"value": [385.24595133463544], "step": 4}]}, "val_accuracy": {"direction": "max", "observations": [{"value": [0.9333333373069763], "step": 4}]}, "val_loss": {"direction": "min", "observations": [{"value": [2601.20263671875], "step": 4}]}}}, "score": 0.9333333373069763, "best_step": 4, "status": "COMPLETED", "message": null}